detquantlib/__init__.py
detquantlib/data/__init__.py
detquantlib/data/databases/detdatabase.py
detquantlib/data/entsoe/entsoe.py
detquantlib/data/sftp/sftp.py
detquantlib/dates/__init__.py
detquantlib/dates/dates.py
detquantlib/figures/__init__.py
detquantlib/figures/plotly_figures.py
detquantlib/forecasting/__init__.py
detquantlib/forecasting/forecasting.py
detquantlib/outputs/__init__.py
detquantlib/outputs/outputs_interface.py
detquantlib/stats/__init__.py
detquantlib/stats/data_analysis.py
detquantlib/tradable_products/__init__.py
detquantlib/tradable_products/tradable_products.py
detquantlib/utils/__init__.py
detquantlib/utils/logging.py
detquantlib/utils/utils.py
detquantlib-3.12.0.dist-info/METADATA
detquantlib-3.12.0.dist-info/WHEEL
detquantlib-3.12.0.dist-info/licenses/LICENSE.txt
detquantlib-3.12.0.dist-info/RECORD
