Metadata-Version: 2.4
Name: detquantlib
Version: 3.12.0
Summary: An internal library containing functions and classes that can be used across Quant models.
License-File: LICENSE.txt
Author: DET
Requires-Python: >=3.10,<4.0
Classifier: Programming Language :: Python :: 3
Classifier: Programming Language :: Python :: 3.10
Classifier: Programming Language :: Python :: 3.11
Classifier: Programming Language :: Python :: 3.12
Classifier: Programming Language :: Python :: 3.13
Classifier: Programming Language :: Python :: 3.14
Requires-Dist: colorlog (>=6.10.1,<7.0.0)
Requires-Dist: numpy (>=2.2.6,<3.0.0)
Requires-Dist: pandas (>=2.3.3,<3.0.0)
Requires-Dist: paramiko (>=4.0.0,<5.0.0)
Requires-Dist: plotly (>=6.3.1,<7.0.0)
Requires-Dist: pyarrow (>=21.0.0,<22.0.0)
Requires-Dist: pyodbc (>=5.2.0,<6.0.0)
Requires-Dist: python-dotenv (>=1.1.0,<2.0.0)
Requires-Dist: scipy (>=1.15.2,<2.0.0)
Requires-Dist: sqlalchemy (>=2.0.43,<3.0.0)
Project-URL: Repository, https://github.com/Dynamic-Energy-Trading/detquantlib
